{
    "configurations": [
        {
            "name": "CMake",
            "compileCommands": "${workspaceFolder}/build/compile_commands.json",
            "configurationProvider": "ms-vscode.cmake-tools",
            "includePath": [
                "${workspaceFolder}/**",
                "${workspaceFolder}/build/esp-idf",
                "${env:IDF_PATH}/components/**"
            ],
            "defines": [],
            "browse": {
                "path": [
                    "${workspaceFolder}/**",
                    "${workspaceFolder}/build/esp-idf",
                    "${env:IDF_PATH}/components/**"
                ],
                "limitSymbolsToIncludedHeaders": true,
                "databaseFilename": ""
            }
        }
    ],
    "version": 4
}